ComputerArc/code/syncbus.v
module master(input clock, w, output [15:0] address, inout [15:0] data);
  reg [15:0] ar, dr;
  assign address = ar;
  assign data = (w)?dr : 16'hzzzz;

  always @(*) begin
    if (!w)
	  dr=#1 data;
  end  
endmodule

module rdevice(input clock, w, input [15:0] address, output [15:0] data);
  reg [15:0] dr;

  assign data=(!w)?dr:16'hZZZZ;
  
  always @(clock or w or address) begin
    if (!w && address == 16'hFFF0)
	  dr = #1 16'he3e3;
  end
endmodule

module wdevice(input clock, w, input [15:0] address, input [15:0] data);
  reg [15:0] dr;
  
  always @(clock or w or address) begin
    if (w && address == 16'hFFF8)
	  dr = #1 data;
  end
endmodule

module main;
reg clock, w;
wire [15:0] abus, dbus;

master  m(clock, w, abus, dbus);
rdevice rd(clock, w, abus, dbus);
wdevice wd(clock, w, abus, dbus);
initial begin
  $monitor("%4dns abus=%x dbus=%x w=%x m.ar=%x m.dr=%x rd.dr=%x wd.dr=%x", $stime, abus, dbus, w, m.ar, m.dr, rd.dr, wd.dr);
  $dumpfile("syncbus.vcd"); // 輸出給 GTK wave 顯示波型
  $dumpvars;    
  clock = 0;
  #10; m.ar=16'h0000; w=0; 
  #50; m.ar=16'hFFF0; 
  #50; m.ar=16'hFFF8; m.dr=16'h71F0; w=1;
  #300; $finish;
end

always #5 clock=~clock; // 每隔 5ns 反相，時脈週期為 10ns
endmodule

ComputerArc/code/syncbus.vcd
$date
	Fri Jul 04 10:44:21 2014
$end
$version
	Icarus Verilog
$end
$timescale
	1s
$end
$scope module main $end
$var wire 16 ! abus [15:0] $end
$var wire 16 " dbus [15:0] $end
$var reg 1 # clock $end
$var reg 1 $ w $end
$scope module m $end
$var wire 16 % address [15:0] $end
$var wire 1 & clock $end
$var wire 16 ' data [15:0] $end
$var wire 1 ( w $end
$var reg 16 ) ar [15:0] $end
$var reg 16 * dr [15:0] $end
$upscope $end
$scope module rd $end
$var wire 16 + address [15:0] $end
$var wire 1 & clock $end
$var wire 16 , data [15:0] $end
$var wire 1 ( w $end
$var reg 16 - dr [15:0] $end
$upscope $end
$scope module wd $end
$var wire 16 . address [15:0] $end
$var wire 1 & clock $end
$var wire 16 / data [15:0] $end
$var wire 1 ( w $end
$var reg 16 0 dr [15:0] $end
$upscope $end
$upscope $end
$enddefinitions $end
#0
$dumpvars
bx 0
bx /
bx .
bx -
bx ,
bx +
bx *
bx )
x(
bx '
0&
bx %
x$
0#
bx "
bx !
$end
#5
1#
1&
#10
0#
0&
0$
0(
b0 )
b0 !
b0 %
b0 +
b0 .
#15
1#
1&
#20
0#
0&
#25
1#
1&
#30
0#
0&
#35
1#
1&
#40
0#
0&
#45
1#
1&
#50
0#
0&
#55
1#
1&
#60
0#
0&
b1111111111110000 )
b1111111111110000 !
b1111111111110000 %
b1111111111110000 +
b1111111111110000 .
#61
b1110001111100011 "
b1110001111100011 '
b1110001111100011 ,
b1110001111100011 /
b1110001111100011 -
#62
b1110001111100011 *
#65
1#
1&
#70
0#
0&
#75
1#
1&
#80
0#
0&
#85
1#
1&
#90
0#
0&
#95
1#
1&
#100
0#
0&
#105
1#
1&
#110
b111000111110000 "
b111000111110000 '
b111000111110000 ,
b111000111110000 /
0#
0&
1$
1(
b111000111110000 *
b1111111111111000 )
b1111111111111000 !
b1111111111111000 %
b1111111111111000 +
b1111111111111000 .
#111
b1110001111100011 0
#115
1#
1&
#116
b111000111110000 0
